COPYING
setup.py
nxdtest/__init__.py
nxdtest/nxdtest_pylint_test.py
nxdtest/nxdtest_pytest_test.py
nxdtest/nxdtest_test.py
nxdtest/nxdtest_unittest_test.py
nxdtest/trun.py
nxdtest.egg-info/PKG-INFO
nxdtest.egg-info/SOURCES.txt
nxdtest.egg-info/dependency_links.txt
nxdtest.egg-info/entry_points.txt
nxdtest.egg-info/requires.txt
nxdtest.egg-info/top_level.txt